skye/__init__.py
skye/core.py
skye/utils.py
skye-0.0.5.dist-info/LICENSE
skye-0.0.5.dist-info/METADATA
skye-0.0.5.dist-info/WHEEL
skye-0.0.5.dist-info/top_level.txt
skye-0.0.5.dist-info/RECORD
